API/Ibp2py.py
API/__init__.py
API/teste.py
ibp2py/__init__.py
ibp2py/ibp2py.py
ibp2py/joblogs.py
ibp2py/teste.py
ibp2py-1.0.6.dist-info/LICENSE
ibp2py-1.0.6.dist-info/METADATA
ibp2py-1.0.6.dist-info/WHEEL
ibp2py-1.0.6.dist-info/top_level.txt
ibp2py-1.0.6.dist-info/RECORD
