Metadata-Version: 2.1
Name: ibp2py
Version: 1.0.6
Summary: SAP Data Retrieval and Processing Library for IBP
Home-page: https://github.com/pedrorastha/ibp2py
Author: Pedro Rastha
Author-email: pedrorastha@gmail.com
Keywords: SAP IBP API ODATA
Classifier: Development Status :: 5 - Production/Stable
Classifier: Intended Audience :: Developers
Classifier: License :: OSI Approved :: Apache Software License
Classifier: Programming Language :: Python :: 3
Classifier: Programming Language :: Python :: 3.6
Classifier: Programming Language :: Python :: 3.7
Classifier: Programming Language :: Python :: 3.8
Classifier: Programming Language :: Python :: 3.9
Classifier: Programming Language :: Python :: 3.10
Classifier: Programming Language :: Python :: 3.11
License-File: LICENSE
Requires-Dist: requests (>=2.20.0)
Requires-Dist: pandas (>=1.2.0)
